{
  "dependencies": {
    "mssql1": {
      "secretStore": "AzureAppSettings",
      "resourceId": "/subscriptions/[parameters('subscriptionId')]/resourceGroups/[parameters('resourceGroupName')]/providers/Microsoft.Sql/servers/sportsstoredbserver7/databases/SportsStore_db",
      "type": "mssql.azure",
      "connectionId": "ConnectionStrings:SportsStoreConnection",
      "dynamicId": null
    },
    "mssql2": {
      "secretStore": "AzureAppSettings",
      "resourceId": "/subscriptions/[parameters('subscriptionId')]/resourcegroups/[parameters('resourceGroupName')]/providers/Microsoft.Sql/servers/identitydbserver/databases/Identity",
      "type": "mssql.azure",
      "connectionId": "ConnectionStrings:IdentityConnection",
      "dynamicId": null
    }
  }
}